hakka/__init__.py
hakka/cli.py
hakka/client.py
hakka/exceptions.py
hakka/hakka.py
hakka/helpers.py
hakka/logging.py
hakka/types.py
hakka/utils.py
hakka-0.2.1.dist-info/DESCRIPTION.rst
hakka-0.2.1.dist-info/METADATA
hakka-0.2.1.dist-info/RECORD
hakka-0.2.1.dist-info/WHEEL
hakka-0.2.1.dist-info/entry_points.txt
hakka-0.2.1.dist-info/metadata.json
hakka-0.2.1.dist-info/top_level.txt
