Metadata-Version: 2.0
Name: hakka
Version: 0.2.1
Summary: Small Task Queue
Home-page: https://github.com/himenon/hakka-py
Author: Kosei Himeno
Author-email: k.himeno314@gmail.com
License: MIT license
Keywords: hakka
Platform: UNKNOWN
Classifier: Development Status :: 2 - Pre-Alpha
Classifier: Intended Audience :: Developers
Classifier: License :: OSI Approved :: MIT License
Classifier: Natural Language :: English
Classifier: Programming Language :: Python :: 3.5
Classifier: Programming Language :: Python :: 3.6
Requires-Dist: Click (>=6.0)
Requires-Dist: redis (>=2.1)
Requires-Dist: six
